breakers/__init__.py
breakers/stats.py
breakers/utils.py
breakers-0.1.0.dist-info/DESCRIPTION.rst
breakers-0.1.0.dist-info/METADATA
breakers-0.1.0.dist-info/metadata.json
breakers-0.1.0.dist-info/RECORD
breakers-0.1.0.dist-info/top_level.txt
breakers-0.1.0.dist-info/WHEEL
